{
  "name": "ZPWR Ember",
  "author": "MenkeTechnologies",
  "dark": true,
  "editorScheme": "/zpwr-ember-dark.xml",
  "colors": {
    "ink": "#0a0502",
    "panel": "#120a04",
    "card": "#1a0e06",
    "hover": "#24140a",
    "border": "#3e2a1a",
    "cyan": "#fb923c",
    "cyanBright": "#fcad6d",
    "pink": "#f59e0b",
    "magenta": "#ea580c",
    "green": "#84cc16",
    "orange": "#f97316",
    "yellow": "#fde047",
    "text": "#fef3c7",
    "textSoft": "#f3ce8d",
    "textDim": "#d97706",
    "muted": "#92400e"
  },
  "ui": {
    "*": {
      "background": "panel",
      "foreground": "text",
      "infoForeground": "textDim",
      "disabledBackground": "ink",
      "disabledForeground": "muted",
      "disabledText": "muted",
      "inactiveForeground": "textDim",
      "selectionBackground": "hover",
      "selectionForeground": "cyan",
      "selectionInactiveBackground": "card",
      "selectionInactiveForeground": "text",
      "borderColor": "border",
      "separatorColor": "border",
      "focusColor": "cyan",
      "focusedBorderColor": "cyan",
      "errorForeground": "pink",
      "acceleratorForeground": "cyan"
    },
    "Editor": {
      "background": "ink",
      "shortcutForeground": "cyan"
    },
    "Panel": {
      "background": "panel",
      "foreground": "text"
    },
    "Borders": {
      "color": "border",
      "ContrastBorderColor": "border"
    },
    "Button": {
      "startBackground": "card",
      "endBackground": "card",
      "foreground": "text",
      "startBorderColor": "border",
      "endBorderColor": "border",
      "focusedBorderColor": "cyan",
      "default": {
        "startBackground": "cyan",
        "endBackground": "cyan",
        "foreground": "ink",
        "startBorderColor": "cyan",
        "endBorderColor": "cyan",
        "focusColor": "cyanBright"
      }
    },
    "Component": {
      "focusColor": "cyan",
      "focusedBorderColor": "cyan",
      "borderColor": "border",
      "errorFocusColor": "pink",
      "warningFocusColor": "yellow"
    },
    "Link": {
      "activeForeground": "cyan",
      "hoverForeground": "cyanBright",
      "visitedForeground": "magenta",
      "pressedForeground": "green"
    },
    "ProgressBar": {
      "progressColor": "cyan",
      "indeterminateStartColor": "cyan",
      "indeterminateEndColor": "magenta",
      "trackColor": "card"
    },
    "TextField": {
      "background": "card",
      "foreground": "text"
    },
    "TextArea": {
      "background": "card",
      "foreground": "text"
    },
    "ComboBox": {
      "background": "card",
      "nonEditableBackground": "card",
      "selectionBackground": "hover",
      "selectionForeground": "cyan"
    },
    "List": {
      "background": "panel",
      "selectionBackground": "hover",
      "selectionForeground": "cyan",
      "selectionInactiveBackground": "card",
      "hoverBackground": "hover"
    },
    "Table": {
      "background": "panel",
      "selectionBackground": "hover",
      "selectionForeground": "cyan",
      "gridColor": "border",
      "stripeColor": "card"
    },
    "Tree": {
      "background": "panel",
      "foreground": "textSoft",
      "selectionBackground": "hover",
      "selectionForeground": "cyan",
      "selectionInactiveBackground": "card",
      "hoverBackground": "hover",
      "hash": "border"
    },
    "Menu": {
      "background": "panel",
      "borderColor": "border",
      "selectionBackground": "hover",
      "selectionForeground": "cyan"
    },
    "MenuItem": {
      "background": "panel",
      "selectionBackground": "hover",
      "selectionForeground": "cyan",
      "acceleratorForeground": "textDim"
    },
    "MenuBar": {
      "background": "ink",
      "borderColor": "border",
      "selectionBackground": "hover",
      "selectionForeground": "cyan"
    },
    "PopupMenu": {
      "background": "panel",
      "borderColor": "border"
    },
    "CompletionPopup": {
      "background": "panel",
      "selectionBackground": "hover",
      "matchForeground": "cyan",
      "matchSelectionForeground": "green"
    },
    "ToolWindow": {
      "Header": {
        "background": "card",
        "inactiveBackground": "panel",
        "borderColor": "border"
      },
      "HeaderTab": {
        "selectedBackground": "hover",
        "selectedInactiveBackground": "card",
        "hoverBackground": "hover",
        "underlineColor": "cyan",
        "inactiveUnderlineColor": "textDim"
      },
      "Button": {
        "selectedBackground": "hover",
        "selectedForeground": "cyan",
        "hoverBackground": "hover"
      }
    },
    "DefaultTabs": {
      "background": "ink",
      "borderColor": "border",
      "underlinedTabBackground": "panel",
      "underlinedTabForeground": "text",
      "underlineColor": "cyan",
      "inactiveUnderlineColor": "textDim",
      "hoverBackground": "hover"
    },
    "EditorTabs": {
      "background": "ink",
      "underlinedTabBackground": "ink",
      "underlinedTabForeground": "text",
      "underlineColor": "cyan",
      "inactiveColoredFileBackground": "panel",
      "hoverBackground": "hover",
      "borderColor": "border"
    },
    "StatusBar": {
      "background": "ink",
      "borderColor": "border",
      "hoverBackground": "hover"
    },
    "NavBar": {
      "borderColor": "border"
    },
    "ScrollBar": {
      "thumbColor": "#3e2a1a80",
      "hoverThumbColor": "#fb923c40"
    },
    "TitlePane": {
      "background": "ink",
      "borderColor": "border",
      "inactiveBackground": "ink"
    },
    "MainToolbar": {
      "background": "ink",
      "Icon": {
        "hoverBackground": "hover"
      },
      "Dropdown": {
        "hoverBackground": "hover"
      }
    },
    "ActionButton": {
      "hoverBackground": "hover",
      "hoverBorderColor": "border",
      "pressedBackground": "card"
    },
    "Notification": {
      "background": "card",
      "borderColor": "border",
      "errorBackground": "#dc262622",
      "errorBorderColor": "pink"
    },
    "Tooltip": {
      "background": "card",
      "borderColor": "border"
    },
    "Counter": {
      "background": "pink",
      "foreground": "ink"
    }
  },
  "icons": {
    "ColorPalette": {
      "Actions.Blue": "#fb923c",
      "Actions.Green": "#84cc16",
      "Actions.Red": "#dc2626",
      "Actions.Yellow": "#fde047",
      "Actions.Grey": "#d97706",
      "Objects.Blue": "#fb923c",
      "Objects.Green": "#84cc16",
      "Objects.Pink": "#f59e0b",
      "Objects.Purple": "#ea580c",
      "Objects.Red": "#dc2626",
      "Objects.Yellow": "#fde047",
      "Objects.Grey": "#d97706"
    }
  }
}
